ieegprep/__init__.py
ieegprep/version.py
ieegprep/bids/__init__.py
ieegprep/bids/data_epoch.py
ieegprep/bids/data_structure.py
ieegprep/bids/rereferencing.py
ieegprep/bids/sidecars.py
ieegprep/fileio/BrainVisionReader.py
ieegprep/fileio/EdfReader.py
ieegprep/fileio/IeegDataReader.py
ieegprep/fileio/Mef3Reader.py
ieegprep/fileio/__init__.py
ieegprep/utils/console.py
ieegprep/utils/misc.py
ieegprep-1.6.1.dist-info/LICENSE
ieegprep-1.6.1.dist-info/METADATA
ieegprep-1.6.1.dist-info/WHEEL
ieegprep-1.6.1.dist-info/top_level.txt
ieegprep-1.6.1.dist-info/RECORD
