Metadata-Version: 2.2
Name: ieegprep
Version: 1.6.1
Summary: A package to read and pre-process Intracranial Electroencephalography (iEEG) data that is structured according to the Brain Imaging Data Structure (BIDS)
Author-email: Max van den Boom <m.a.vandenboom84@gmail.com>
License: GPLv3
Project-URL: homepage, https://github.com/MultimodalNeuroimagingLab/ieegprep
Project-URL: documentation, https://github.com/MultimodalNeuroimagingLab/ieegprep
Project-URL: repository, https://github.com/MultimodalNeuroimagingLab/ieegprep
Keywords: intracranial,electroencephalography,ieeg,BIDS
Classifier: Intended Audience :: Science/Research
Classifier: License :: OSI Approved :: GNU General Public License v3 (GPLv3)
Classifier: Operating System :: OS Independent
Classifier: Programming Language :: Python :: 3
Classifier: Programming Language :: Python :: 3 :: Only
Classifier: Programming Language :: Python :: 3.13
Classifier: Programming Language :: Python :: 3.12
Classifier: Programming Language :: Python :: 3.11
Classifier: Programming Language :: Python :: 3.10
Classifier: Programming Language :: Python :: 3.9
Classifier: Topic :: Scientific/Engineering
Requires-Python: >=3.9
License-File: LICENSE
Requires-Dist: numpy>=2.2.1
Requires-Dist: scipy>=1.15.0
Requires-Dist: pymef>=1.4.5
Requires-Dist: psutil>=6.1.1
